[
  {
    "id": 1,
    "title": {
      "it": "Automated Bin Picking",
      "en": "Automated Bin Picking"
    },
    "description": {
      "it": "Sistema di visione 3D per il prelievo di componenti disposti casualmente in contenitori industriali.",
      "en": "3D vision system for picking randomly arranged components in industrial containers."
    },
    "videoUrl": "https://res.cloudinary.com/instinctrobotics/video/upload/v1774625027/simulation_hzlfvu.mp4",
    "thumbnail": "https://images.unsplash.com/photo-1581091226825-a6a2a5aee158?auto=format&fit=crop&q=80&w=800",
    "tags": [
      "3D Vision",
      "Automation",
      "Precision"
    ]
  },
  {
    "id": 2,
    "title": {
      "it": "Food Sorting AI",
      "en": "Food Sorting AI"
    },
    "description": {
      "it": "Riconoscimento e smistamento di prodotti alimentari con forme irregolari e variabili.",
      "en": "Recognition and sorting of food products with irregular and variable shapes."
    },
    "videoUrl": "https://res.cloudinary.com/instinctrobotics/video/upload/v1774625027/simulation_hzlfvu.mp4",
    "thumbnail": "https://images.unsplash.com/photo-1516382799247-6319b1ad7dcf?auto=format&fit=crop&q=80&w=800",
    "tags": [
      "Agnostic AI",
      "Food Industry"
    ]
  },
  {
    "id": 3,
    "title": {
      "it": "Universal Arm Integration",
      "en": "Universal Arm Integration"
    },
    "description": {
      "it": "Integrazione del nostro software con diversi bracci robotici tramite un'unica interfaccia agnostica.",
      "en": "Integration of our software with different robotic arms through a single agnostic interface."
    },
    "videoUrl": "https://res.cloudinary.com/instinctrobotics/video/upload/v1774625027/simulation_hzlfvu.mp4",
    "thumbnail": "https://images.unsplash.com/photo-1565515467012-1811565551f3?auto=format&fit=crop&q=80&w=800",
    "tags": [
      "Hardware Agnostic",
      "Universal Integration"
    ]
  }
]